Workbook

Sheet Table_Income
A1: INCOME STATEMENT
A3: Quarter | B3: Revenue | C3: Cost_of_Goods_Sold | D3: Gross_Profit | E3: Operating_Expenses | F3: EBITDA | G3: Depreciation_Amortization | H3: EBIT | I3: Interest_Expense | J3: EBT | K3: Tax_Expense | L3: Net_Income
A4: Q1 2025 | B4: 12500000 | C4: 6250000 | D4: 6250000 | E4: 3125000 | F4: 3125000 | G4: 625000 | H4: 2500000 | I4: 312500 | J4: 2187500 | K4: 546875 | L4: 1640625
A5: Q2 2025 | B5: 14375000 | C5: 6900000 | D5: 7475000 | E5: 3594000 | F5: 3881000 | G5: 656250 | H5: 3224750 | I5: 300000 | J5: 2924750 | K5: 731188 | L5: 2193562
A6: Q3 2025 | B6: 16750000 | C6: 7537500 | D6: 9212500 | E6: 4187500 | F6: 5025000 | G6: 693750 | H6: 4331250 | I6: 281250 | J6: 4050000 | K6: 1012500 | L6: 3037500
A7: Q4 2025 | B7: 19500000 | C7: 8190000 | D7: 11310000 | E7: 4875000 | F7: 6435000 | G7: 731250 | H7: 5703750 | I7: 262500 | J7: 5441250 | K7: 1360313 | L7: 4080937

Sheet Table_Balance
A1: BALANCE SHEET
A3: Quarter | B3: Cash_and_Equivalents | C3: Accounts_Receivable | D3: Inventory | E3: Prepaid_Expenses | F3: Current_Assets | G3: PP_E | H3: Intangible_Assets | I3: Other_Long_Term_Assets | J3: Total_Assets | K3: Accounts_Payable | L3: Short_Term_Debt | M3: Accrued_Expenses | N3: Current_Liabilities | O3: Long_Term_Debt | P3: Deferred_Tax_Liabilities | Q3: Other_Long_Term_Liabilities | R3: Total_Liabilities | S3: Common_Stock | T3: Retained_Earnings | U3: Total_Equity
A4: Q1 2025 | B4: 4500000 | C4: 3200000 | D4: 2800000 | E4: 350000 | F4: 10850000 | G4: 18750000 | H4: 8500000 | I4: 1900000 | J4: 40000000 | K4: 2100000 | L4: 2500000 | M4: 875000 | N4: 5475000 | O4: 12500000 | P4: 1800000 | Q4: 1225000 | R4: 21000000 | S4: 5000000 | T4: 14000000 | U4: 19000000
A5: Q2 2025 | B5: 5800000 | C5: 3680000 | D5: 2900000 | E5: 370000 | F5: 12750000 | G5: 19500000 | H5: 8350000 | I5: 2000000 | J5: 42600000 | K5: 2250000 | L5: 2250000 | M5: 920000 | N5: 5420000 | O5: 11750000 | P5: 1780000 | Q5: 1250000 | R5: 20200000 | S5: 5000000 | T5: 17400000 | U5: 22400000
A6: Q3 2025 | B6: 7200000 | C6: 4300000 | D6: 3100000 | E6: 400000 | F6: 15000000 | G6: 20100000 | H6: 8200000 | I6: 2100000 | J6: 45400000 | K6: 2400000 | L6: 2000000 | M6: 980000 | N6: 5380000 | O6: 11000000 | P6: 1750000 | Q6: 1270000 | R6: 19400000 | S6: 5000000 | T6: 21000000 | U6: 26000000
A7: Q4 2025 | B7: 9100000 | C7: 5070000 | D7: 3250000 | E7: 430000 | F7: 17850000 | G7: 20550000 | H7: 8050000 | I7: 2200000 | J7: 48650000 | K7: 2550000 | L7: 1750000 | M7: 1050000 | N7: 5350000 | O7: 10250000 | P7: 1720000 | Q7: 1280000 | R7: 18600000 | S7: 5000000 | T7: 25050000 | U7: 30050000

Sheet Dashboard
A1: AURELIUS STRATEGIC HOLDINGS | Z1: =IFERROR(INDEX(Table_Income!$B$4:$B$7,MATCH($C$4,Table_Income!$A$4:$A$7,0)),"") -> 19500000
A2: Financial Command Centre FY 2025 | Z2: =IFERROR(INDEX(Table_Income!$D$4:$D$7,MATCH($C$4,Table_Income!$A$4:$A$7,0)),"") -> 11310000
Z3: =IFERROR(INDEX(Table_Income!$L$4:$L$7,MATCH($C$4,Table_Income!$A$4:$A$7,0)),"") -> 4080937
B4: SELECT QUARTER: | C4: Q4 2025 | Z4: =IFERROR(INDEX(Table_Balance!$F$4:$F$7,MATCH($C$4,Table_Balance!$A$4:$A$7,0)),"") -> 17850000
Z5: =IFERROR(INDEX(Table_Balance!$N$4:$N$7,MATCH($C$4,Table_Balance!$A$4:$A$7,0)),"") -> 5350000
Z6: =IFERROR(INDEX(Table_Balance!$B$4:$B$7,MATCH($C$4,Table_Balance!$A$4:$A$7,0)),"") -> 9100000 | BN6: Current Ratio | BR6: Quick Ratio | BV6: Gross Margin | BZ6: Net Profit Margin
B7: =IF(Z4="","-",Z4/Z5) -> 3.3364486 | F7: =IF(Z4="","-",(Z4-Z7)/Z5) -> 2.728972 | J7: =IF(Z2="","-",Z2/Z1) -> 0.58 | N7: =IF(Z3="","-",Z3/Z1) -> 0.20927882 | Z7: =IFERROR(INDEX(Table_Balance!$D$4:$D$7,MATCH($C$4,Table_Balance!$A$4:$A$7,0)),"") -> 3250000 | BN7: =IFERROR(Z4/Z5,"-") -> 3.3364486 | BR7: =IFERROR((Z4-Z7)/Z5,"-") -> 2.728972 | BV7: =IFERROR(Z2/Z1,"-") -> 0.58 | BZ7: =IFERROR(Z3/Z1,"-") -> 0.20927882
Z8: =IFERROR(INDEX(Table_Balance!$R$4:$R$7,MATCH($C$4,Table_Balance!$A$4:$A$7,0)),"") -> 18600000
Z9: =IFERROR(INDEX(Table_Balance!$U$4:$U$7,MATCH($C$4,Table_Balance!$A$4:$A$7,0)),"") -> 30050000
Z10: =IFERROR(INDEX(Table_Income!$H$4:$H$7,MATCH($C$4,Table_Income!$A$4:$A$7,0)),"") -> 5703750 | BN10: ROE | BR10: Debt-to-Equity | BV10: Interest Coverage | BZ10: Asset Growth (QoQ)
B11: =IF(Z3="","-",Z3/Z9) -> 0.13580489 | F11: =IF(Z8="","-",Z8/Z9) -> 0.61896839 | J11: =IF(Z11="","-",Z10/Z11) -> 21.728571 | N11: =IF($C$4="Q1 2025","",IF($C$4="Q2 2025", (INDEX(Table_Balance!$J$4:$J$7,MATCH("Q2 2025",Table_Balance!$A$4:$A$7,0))/ INDEX(Table_Balance!$J$4:$J$7,MATCH("Q1 2025",Table_Balance!$A$4:$A$7,0))-1), IF($C$4="Q3 2025", (INDEX(Table_Balance!$J$4:$J$7,MATCH("Q3 2025",Table_Balance!$A$4:$A$7,0))/ INDEX(Table_Balance!$J$4:$J$7,MATCH("Q2 2025",Table_Balance!$A$4:$A$7,0))-1), IF($C$4="Q4 2025", (INDEX(Table_Balance!$J$4:$J$7,MATCH("Q4 2025",Table_Balance!$A$4:$A$7,0))/ INDEX(Table_Balance!$J$4:$J$7,MATCH("Q3 2025",Table_Balance!$A$4:$A$7,0))-1), "")))) -> 0.071585903 | Z11: =IFERROR(INDEX(Table_Income!$I$4:$I$7,MATCH($C$4,Table_Income!$A$4:$A$7,0)),"") -> 262500 | BN11: =IFERROR(Z3/Z9,"-") -> 0.13580489 | BR11: =IFERROR(Z8/Z9,"-") -> 0.61896839 | BV11: =IFERROR(Z10/Z11,"-") -> 21.728571 | BZ11: =IFERROR((_xludf.xlookup($C$4,#REF!,#REF!)/_xludf.xlookup(IF($C$4="Q1 2025","Q4 2024",IF($C$4="Q2 2025","Q1 2025",IF($C$4="Q3 2025","Q2 2025","Q3 2025"))),#REF!,#REF!))-1,"-") -> -
Z12: =IFERROR(INDEX(Table_Balance!$J$4:$J$7,MATCH($C$4,Table_Balance!$A$4:$A$7,0)),"") -> 48650000
B15: Chart Data
B16: Q1 2025 | C16: Q2 2025 | D16: Q3 2025 | E16: Q4 2025 | H16: Financial Metrics | I16: Q4 2025
A17: Revenue | B17: =INDEX(Table_Income!$B$4:$B$7,MATCH("Q1 2025",Table_Income!$A$4:$A$7,0)) -> 12500000 | C17: =INDEX(Table_Income!$B$4:$B$7,MATCH("Q2 2025",Table_Income!$A$4:$A$7,0)) -> 14375000 | D17: =INDEX(Table_Income!$B$4:$B$7,MATCH("Q3 2025",Table_Income!$A$4:$A$7,0)) -> 16750000 | E17: =INDEX(Table_Income!$B$4:$B$7,MATCH("Q4 2025",Table_Income!$A$4:$A$7,0)) -> 19500000 | H17: Current Ratio | I17: =INDEX(Table_Balance!$F$4:$F$7,MATCH("Q4 2025",Table_Balance!$A$4:$A$7,0))/INDEX(Table_Balance!$N$4:$N$7,MATCH("Q4 2025",Table_Balance!$A$4:$A$7,0)) -> 3.3364486
A18: Net Income | B18: =INDEX(Table_Income!$L$4:$L$7,MATCH("Q1 2025",Table_Income!$A$4:$A$7,0)) -> 1640625 | C18: =INDEX(Table_Income!$L$4:$L$7,MATCH("Q2 2025",Table_Income!$A$4:$A$7,0)) -> 2193562 | D18: =INDEX(Table_Income!$L$4:$L$7,MATCH("Q3 2025",Table_Income!$A$4:$A$7,0)) -> 3037500 | E18: =INDEX(Table_Income!$L$4:$L$7,MATCH("Q4 2025",Table_Income!$A$4:$A$7,0)) -> 4080937 | H18: Quick Ratio | I18: =(INDEX(Table_Balance!$F$4:$F$7,MATCH("Q4 2025",Table_Balance!$A$4:$A$7,0))-INDEX(Table_Balance!$D$4:$D$7,MATCH("Q4 2025",Table_Balance!$A$4:$A$7,0)))/INDEX(Table_Balance!$N$4:$N$7,MATCH("Q4 2025",Table_Balance!$A$4:$A$7,0)) -> 2.728972
A19: Operating Expenses | B19: =INDEX(Table_Income!$E$4:$E$7,MATCH("Q1 2025",Table_Income!$A$4:$A$7,0)) -> 3125000 | C19: =INDEX(Table_Income!$E$4:$E$7,MATCH("Q2 2025",Table_Income!$A$4:$A$7,0)) -> 3594000 | D19: =INDEX(Table_Income!$E$4:$E$7,MATCH("Q3 2025",Table_Income!$A$4:$A$7,0)) -> 4187500 | E19: =INDEX(Table_Income!$E$4:$E$7,MATCH("Q4 2025",Table_Income!$A$4:$A$7,0)) -> 4875000 | H19: ROE (%) | I19: =INDEX(Table_Income!$L$4:$L$7,MATCH("Q4 2025",Table_Income!$A$4:$A$7,0))/INDEX(Table_Balance!$U$4:$U$7,MATCH("Q4 2025",Table_Balance!$A$4:$A$7,0))*100 -> 13.580489
H20: Interest Cov | I20: =INDEX(Table_Income!$H$4:$H$7,MATCH("Q4 2025",Table_Income!$A$4:$A$7,0))/INDEX(Table_Income!$I$4:$I$7,MATCH("Q4 2025",Table_Income!$A$4:$A$7,0)) -> 21.728571
A21: Total Assets | B21: =INDEX(Table_Balance!$J$4:$J$7,MATCH("Q1 2025",Table_Balance!$A$4:$A$7,0)) -> 40000000 | C21: =INDEX(Table_Balance!$J$4:$J$7,MATCH("Q2 2025",Table_Balance!$A$4:$A$7,0)) -> 42600000 | D21: =INDEX(Table_Balance!$J$4:$J$7,MATCH("Q3 2025",Table_Balance!$A$4:$A$7,0)) -> 45400000 | E21: =INDEX(Table_Balance!$J$4:$J$7,MATCH("Q4 2025",Table_Balance!$A$4:$A$7,0)) -> 48650000 | H21: Asset Growth (%) | I21: =(INDEX(Table_Balance!$J$4:$J$7,MATCH("Q4 2025",Table_Balance!$A$4:$A$7,0))/INDEX(Table_Balance!$J$4:$J$7,MATCH("Q3 2025",Table_Balance!$A$4:$A$7,0))-1)*100 -> 7.1585903
A22: Total Liabilities | B22: =INDEX(Table_Balance!$R$4:$R$7,MATCH("Q1 2025",Table_Balance!$A$4:$A$7,0)) -> 21000000 | C22: =INDEX(Table_Balance!$R$4:$R$7,MATCH("Q2 2025",Table_Balance!$A$4:$A$7,0)) -> 20200000 | D22: =INDEX(Table_Balance!$R$4:$R$7,MATCH("Q3 2025",Table_Balance!$A$4:$A$7,0)) -> 19400000 | E22: =INDEX(Table_Balance!$R$4:$R$7,MATCH("Q4 2025",Table_Balance!$A$4:$A$7,0)) -> 18600000
B25: Executive Insights:
B26: =IF(Z1="","Select a quarter to view insights","For " & $C$4 & ": Revenue reached " & TEXT(Z1,"$#,##0") & " with a " & TEXT(Z3/Z1,"0.0%") & " net margin. Balance sheet strength improved with Debt-to-Equity at " & TEXT(Z8/Z9,"0.00") & " and Current Ratio of " & TEXT(Z4/Z5,"0.00") & ". Interest coverage stands at " & TEXT(Z10/Z11,"0.0") & "x, indicating " & IF(Z10/Z11>5,"strong","adequate") & " debt servicing capacity.") -> For Q4 2025: Revenue reached $19,500,000 with a 20.9% net margin. Balance sheet strength improved with Debt-to-Equity at 0.62 and Current Ratio of 3.34. Interest coverage stands at 21.7x, indicating strong debt servicing capacity.
